protonup/__init__.py
protonup/__main__.py
protonup/api.py
protonup/cli.py
protonup/constants.py
protonup/utilities.py
protonup_ng-0.2.1.dist-info/LICENSE
protonup_ng-0.2.1.dist-info/METADATA
protonup_ng-0.2.1.dist-info/WHEEL
protonup_ng-0.2.1.dist-info/entry_points.txt
protonup_ng-0.2.1.dist-info/top_level.txt
protonup_ng-0.2.1.dist-info/RECORD
