Metadata-Version: 2.1
Name: protonup-ng
Version: 0.2.1
Summary: Manage Proton-GE Installations
Home-page: https://github.com/cloudishBenne/protonup-ng
Author: cloudishBenne
License: GPL-3.0
Platform: UNKNOWN
Requires-Python: >3.6
License-File: LICENSE
Requires-Dist: requests
Requires-Dist: configparser
